tabshot/__init__.py
tabshot/__main__.py
tabshot/func_listeners.py
tabshot/func_load.py
tabshot/func_print.py
tabshot/func_save.py
tabshot-1.0.0.dist-info/METADATA
tabshot-1.0.0.dist-info/WHEEL
tabshot-1.0.0.dist-info/entry_points.txt
tabshot-1.0.0.dist-info/RECORD
