Metadata-Version: 2.3
Name: tabshot
Version: 1.0.0
Summary: copy all tab URLs from a browser window
Project-URL: Repository, https://github.com/iso1048/tabshot
Keywords: browser,url
Classifier: License :: OSI Approved :: MIT License
Classifier: Operating System :: OS Independent
Classifier: Programming Language :: Python :: 3
Requires-Python: >=3.8
